setup.cfg
setup.py
fakenews_detector/__init__.py
fakenews_detector/categories_dict.py
fakenews_detector/domain_checker.py
fakenews_detector/main.py
fakenews_detector/news_info.py
fakenews_detector/url_utils.py
fakenews_detector.egg-info/PKG-INFO
fakenews_detector.egg-info/SOURCES.txt
fakenews_detector.egg-info/dependency_links.txt
fakenews_detector.egg-info/not-zip-safe
fakenews_detector.egg-info/requires.txt
fakenews_detector.egg-info/top_level.txt
fakenews_detector/fake_fact_ai/RandomForest.py
fakenews_detector/fake_fact_ai/RandomTree.py
fakenews_detector/fake_fact_ai/application.py
fakenews_detector/fake_fact_ai/feature.py
fakenews_detector/fake_fact_ai/finalModel.py
fakenews_detector/fake_fact_ai/settings.py
fakenews_detector/fake_fact_ai/static/fake2.txt
fakenews_detector/fake_fact_ai/static/real2.txt
fakenews_detector/json_local/categories.json
fakenews_detector/json_local/fake_news_sites.json
fakenews_detector/json_local/manualy_added_sites.json
fakenews_detector/json_local/opensources/sources.json
fakenews_detector/json_local/opensources/tags.json
fakenews_detector/tests/__init__.py
fakenews_detector/tests/test_url_utils.py