Metadata-Version: 1.1
Name: fakenews-detector
Version: 0.1.29
Summary: Detect fake and get information about the source.
Home-page: https://github.com/
Author: Mieszko Makuch
Author-email: mmakuch@googlemail.com
License: UNKNOWN
Download-URL: https://mieszko_makuch@bitbucket.org/mieszko_makuch/fakenews_detector.git
Keywords: fakenews,fake,news,detector
Platform: UNKNOWN
